chunkmuncher/__init__.py
chunkmuncher/chunk.py
chunkmuncher-0.0.2.dist-info/LICENSE
chunkmuncher-0.0.2.dist-info/METADATA
chunkmuncher-0.0.2.dist-info/WHEEL
chunkmuncher-0.0.2.dist-info/top_level.txt
chunkmuncher-0.0.2.dist-info/RECORD
