Metadata-Version: 2.1
Name: chunkmuncher
Version: 0.0.2
Summary: Recharge of the chunk module that was removed as of Python 3.13.
Home-page: https://github.com/jscuster/ChunkMuncher
Author: Jason Custer
Author-email: jscuster@gmail.com
License: PSF-2.0
Keywords: python chunk IFF PEP594
Classifier: Development Status :: 3 - Alpha
Classifier: Topic :: Utilities
Classifier: Topic :: File Formats
Classifier: License :: OSI Approved :: Python Software Foundation License
Classifier: Intended Audience :: Developers
Classifier: Natural Language :: English
Classifier: Programming Language :: Python
License-File: LICENSE
